[
  {
    "_id": "2025-06-10T00:00:00",
    "forecast": 0,
    "actual": 0,
    "export": 0.0,
    "carbon_emission": 0,
    "price": 7.0
  },
  {
    "_id": "2025-06-10T00:30:00",
    "forecast": 0,
    "actual": 0,
    "export": 0.0,
    "carbon_emission": 0,
    "price": 7.0
  },
  {
    "_id": "2025-06-10T01:00:00",
    "forecast": 0,
    "actual": 0,
    "export": 0.0,
    "carbon_emission": 0,
    "price": 7.0
  },
  {
    "_id": "2025-06-10T01:30:00",
    "forecast": 0,
    "actual": 0,
    "export": 0.0,
    "carbon_emission": 0,
    "price": 7.0
  },
  {
    "_id": "2025-06-10T02:00:00",
    "forecast": 0,
    "actual": 0,
    "export": 0.0,
    "carbon_emission": 0,
    "price": 7.0
  },
  {
    "_id": "2025-06-10T02:30:00",
    "forecast": 0,
    "actual": 4.41136523030599,
    "export": 0.0,
    "carbon_emission": 0.939620794055176,
    "price": 7.0
  },
  {
    "_id": "2025-06-10T03:00:00",
    "forecast": 0,
    "actual": 4.445289172363281,
    "export": 0.0,
    "carbon_emission": 0.9468465937133789,
    "price": 7.0
  },
  {
    "_id": "2025-06-10T03:30:00",
    "forecast": 0,
    "actual": 4.47651481391059,
    "export": 0.0,
    "carbon_emission": 0.9534976553629557,
    "price": 7.0
  },
  {
    "_id": "2025-06-10T04:00:00",
    "forecast": 0,
    "actual": 4.466390671115452,
    "export": 0.0,
    "carbon_emission": 0.9513412129475912,
    "price": 7.0
  },
  {
    "_id": "2025-06-10T04:30:00",
    "forecast": 0,
    "actual": 4.453877920193142,
    "export": 0.0,
    "carbon_emission": 0.9486759970011394,
    "price": 7.0
  },
  {
    "_id": "2025-06-10T05:00:00",
    "forecast": 0,
    "actual": 3.9846468153211805,
    "export": 0.0,
    "carbon_emission": 0.8487297716634115,
    "price": 7.0
  },
  {
    "_id": "2025-06-10T05:30:00",
    "forecast": 0,
    "actual": 2.968937794325087,
    "export": 0.0,
    "carbon_emission": 0.6323837501912435,
    "price": 7.0
  },
  {
    "_id": "2025-06-10T06:00:00",
    "forecast": 0,
    "actual": 4.245948383246527,
    "export": 0.0,
    "carbon_emission": 0.25900285137803813,
    "price": 7.0
  },
  {
    "_id": "2025-06-10T06:30:00",
    "forecast": 0,
    "actual": 4.440356766101926,
    "export": 0.0,
    "carbon_emission": 0.9457959911797104,
    "price": 7.0
  },
  {
    "_id": "2025-06-10T07:00:00",
    "forecast": 0,
    "actual": 7.93517549210021,
    "export": 0.0,
    "carbon_emission": 1.6901923798173446,
    "price": 7.0
  },
  {
    "_id": "2025-06-10T07:30:00",
    "forecast": 0,
    "actual": 14.67914548611111,
    "export": 0.0,
    "carbon_emission": 3.126657988541667,
    "price": 7.0
  },
  {
    "_id": "2025-06-10T08:00:00",
    "forecast": 0,
    "actual": 16.011476779513888,
    "export": 0.0,
    "carbon_emission": 3.410444554036458,
    "price": 7.0
  },
  {
    "_id": "2025-06-10T08:30:00",
    "forecast": 0,
    "actual": 15.724874207899305,
    "export": 0.0,
    "carbon_emission": 3.3493982062825522,
    "price": 7.0
  },
  {
    "_id": "2025-06-10T09:00:00",
    "forecast": 0,
    "actual": 16.640159364149305,
    "export": 0.0,
    "carbon_emission": 3.544353944563802,
    "price": 7.0
  },
  {
    "_id": "2025-06-10T09:30:00",
    "forecast": 0,
    "actual": 18.019811480034722,
    "export": 0.0,
    "carbon_emission": 3.8382198452473957,
    "price": 7.0
  },
  {
    "_id": "2025-06-10T10:00:00",
    "forecast": 0,
    "actual": 18.00013082470414,
    "export": 0.0,
    "carbon_emission": 3.8340278656619815,
    "price": 7.0
  },
  {
    "_id": "2025-06-10T10:30:00",
    "forecast": 0,
    "actual": 18.273730185231855,
    "export": 0.0,
    "carbon_emission": 3.8923045294543854,
    "price": 7.0
  },
  {
    "_id": "2025-06-10T11:00:00",
    "forecast": 0,
    "actual": 17.61055932074653,
    "export": 0.0,
    "carbon_emission": 3.7510491353190103,
    "price": 7.0
  },
  {
    "_id": "2025-06-10T11:30:00",
    "forecast": 0,
    "actual": 16.407045632595487,
    "export": 0.0,
    "carbon_emission": 3.494700719742839,
    "price": 7.0
  },
  {
    "_id": "2025-06-10T12:00:00",
    "forecast": 0,
    "actual": 15.489381792534722,
    "export": 0.0,
    "carbon_emission": 3.299238321809896,
    "price": 7.0
  },
  {
    "_id": "2025-06-10T12:30:00",
    "forecast": 0,
    "actual": 16.205604453997903,
    "export": 0.0,
    "carbon_emission": 3.4517937487015535,
    "price": 7.0
  },
  {
    "_id": "2025-06-10T13:00:00",
    "forecast": 0,
    "actual": 18.594122298177084,
    "export": 0.0,
    "carbon_emission": 3.960548049511719,
    "price": 7.0
  },
  {
    "_id": "2025-06-10T13:30:00",
    "forecast": 0,
    "actual": 19.74790673828125,
    "export": 0.0,
    "carbon_emission": 4.206304135253907,
    "price": 7.0
  },
  {
    "_id": "2025-06-10T14:00:00",
    "forecast": 0,
    "actual": 17.698475754034323,
    "export": 0.0,
    "carbon_emission": 3.7697753356093107,
    "price": 7.0
  },
  {
    "_id": "2025-06-10T14:30:00",
    "forecast": 0,
    "actual": 16.052975011160715,
    "export": 0.0,
    "carbon_emission": 3.4192836773772326,
    "price": 7.0
  },
  {
    "_id": "2025-06-10T15:00:00",
    "forecast": 0,
    "actual": 0,
    "export": 0,
    "carbon_emission": 0,
    "price": 7.0
  },
  {
    "_id": "2025-06-10T15:30:00",
    "forecast": 0,
    "actual": 0,
    "export": 0,
    "carbon_emission": 0,
    "price": 7.0
  },
  {
    "_id": "2025-06-10T16:00:00",
    "forecast": 0,
    "actual": 0,
    "export": 0,
    "carbon_emission": 0,
    "price": 7.0
  },
  {
    "_id": "2025-06-10T16:30:00",
    "forecast": 0,
    "actual": 0,
    "export": 0,
    "carbon_emission": 0,
    "price": 7.0
  },
  {
    "_id": "2025-06-10T17:00:00",
    "forecast": 0,
    "actual": 0,
    "export": 0,
    "carbon_emission": 0,
    "price": 7.0
  },
  {
    "_id": "2025-06-10T17:30:00",
    "forecast": 0,
    "actual": 0,
    "export": 0,
    "carbon_emission": 0,
    "price": 7.0
  },
  {
    "_id": "2025-06-10T18:00:00",
    "forecast": 0,
    "actual": 0,
    "export": 0,
    "carbon_emission": 0,
    "price": 7.0
  },
  {
    "_id": "2025-06-10T18:30:00",
    "forecast": 0,
    "actual": 0,
    "export": 0,
    "carbon_emission": 0,
    "price": 7.0
  },
  {
    "_id": "2025-06-10T19:00:00",
    "forecast": 0,
    "actual": 0,
    "export": 0,
    "carbon_emission": 0,
    "price": 7.0
  },
  {
    "_id": "2025-06-10T19:30:00",
    "forecast": 0,
    "actual": 0,
    "export": 0,
    "carbon_emission": 0,
    "price": 7.0
  },
  {
    "_id": "2025-06-10T20:00:00",
    "forecast": 0,
    "actual": 0,
    "export": 0,
    "carbon_emission": 0,
    "price": 7.0
  },
  {
    "_id": "2025-06-10T20:30:00",
    "forecast": 0,
    "actual": 0,
    "export": 0,
    "carbon_emission": 0,
    "price": 7.0
  },
  {
    "_id": "2025-06-10T21:00:00",
    "forecast": 0,
    "actual": 0,
    "export": 0,
    "carbon_emission": 0,
    "price": 7.0
  },
  {
    "_id": "2025-06-10T21:30:00",
    "forecast": 0,
    "actual": 0,
    "export": 0,
    "carbon_emission": 0,
    "price": 7.0
  },
  {
    "_id": "2025-06-10T22:00:00",
    "forecast": 0,
    "actual": 0,
    "export": 0,
    "carbon_emission": 0,
    "price": 7.0
  },
  {
    "_id": "2025-06-10T22:30:00",
    "forecast": 0,
    "actual": 0,
    "export": 0,
    "carbon_emission": 0,
    "price": 7.0
  },
  {
    "_id": "2025-06-10T23:00:00",
    "forecast": 0,
    "actual": 0,
    "export": 0,
    "carbon_emission": 0,
    "price": 7.0
  },
  {
    "_id": "2025-06-10T23:30:00",
    "forecast": 0,
    "actual": 0,
    "export": 0,
    "carbon_emission": 0,
    "price": 7.0
  }
]